py_webscrapper-0.1.0.dist-info/licenses/LICENSE
webscraper/__init__.py
webscraper/cli.py
webscraper/scraper.py
webscraper/utils.py
webscraper/extraction/__init__.py
webscraper/extraction/document.py
webscraper/extraction/image.py
py_webscrapper-0.1.0.dist-info/METADATA
py_webscrapper-0.1.0.dist-info/WHEEL
py_webscrapper-0.1.0.dist-info/entry_points.txt
py_webscrapper-0.1.0.dist-info/top_level.txt
py_webscrapper-0.1.0.dist-info/RECORD
