Metadata-Version: 2.4
Name: py-webscrapper
Version: 0.1.0
Summary: A versatile web scraping library for extracting content from websites
Home-page: https://github.com/dhruvldrp9/WebScrapper-PyPI
Author: Dhruvkumar Patel
Author-email: dhruv.ldrp9@gmail.com
Classifier: Development Status :: 4 - Beta
Classifier: Intended Audience :: Developers
Classifier: License :: OSI Approved :: MIT License
Classifier: Programming Language :: Python :: 3
Classifier: Programming Language :: Python :: 3.7
Classifier: Programming Language :: Python :: 3.8
Classifier: Programming Language :: Python :: 3.9
Classifier: Programming Language :: Python :: 3.10
Classifier: Topic :: Internet :: WWW/HTTP
Classifier: Topic :: Software Development :: Libraries :: Python Modules
Classifier: Topic :: Text Processing :: Markup :: HTML
Requires-Python: >=3.7
License-File: LICENSE
Requires-Dist: requests>=2.25.0
Requires-Dist: beautifulsoup4>=4.9.0
Requires-Dist: spacy>=3.0.0
Requires-Dist: chardet>=4.0.0
Provides-Extra: pdf
Requires-Dist: PyPDF2>=2.0.0; extra == "pdf"
Provides-Extra: docx
Requires-Dist: python-docx>=0.8.11; extra == "docx"
Provides-Extra: excel
Requires-Dist: openpyxl>=3.0.7; extra == "excel"
Provides-Extra: ocr
Requires-Dist: pytesseract>=0.3.8; extra == "ocr"
Requires-Dist: Pillow>=8.0.0; extra == "ocr"
Provides-Extra: all
Requires-Dist: PyPDF2>=2.0.0; extra == "all"
Requires-Dist: python-docx>=0.8.11; extra == "all"
Requires-Dist: openpyxl>=3.0.7; extra == "all"
Requires-Dist: pytesseract>=0.3.8; extra == "all"
Requires-Dist: Pillow>=8.0.0; extra == "all"
Provides-Extra: dev
Requires-Dist: pytest>=6.0.0; extra == "dev"
Requires-Dist: pytest-cov>=2.12.0; extra == "dev"
Requires-Dist: black>=21.5b2; extra == "dev"
Requires-Dist: flake8>=3.9.0; extra == "dev"
Requires-Dist: isort>=5.9.0; extra == "dev"
Dynamic: author
Dynamic: author-email
Dynamic: classifier
Dynamic: description
Dynamic: description-content-type
Dynamic: home-page
Dynamic: license-file
Dynamic: provides-extra
Dynamic: requires-dist
Dynamic: requires-python
Dynamic: summary
